source_code/Even_Pipe.v
module Even_Pipe(
  input clk,
  input rst,

  input [0:31] full_isntr,
  input [0:6] instr_id,
  input [0:6] reg_dst,
  input [0:2] unit_id,
  input [0:3] latency,
  input reg_wr,

  input [0:127] ra_data,
  input [0:127] rb_data,
  input [0:127] rc_data, // rc port is also used for instructions that need rt data as an operand
  input [0:7] imme7,
  input [0:9] imme10,
  input [0:15] imme16,
  input [0:17] imme18,




  // output for forwarding unit
  output reg [0:142] packed_result_1stage,
  output reg [0:142] packed_result_2stage,
  output reg [0:142] packed_result_3stage,
  output reg [0:142] packed_result_4stage,
  output reg [0:142] packed_result_5stage,
  output reg [0:142] packed_result_6stage,
  output reg [0:142] packed_result_7stage,

  // Write back stage
  output reg [0:6] WB_reg_write_addr,
  output reg [0:127] WB_reg_write_data,
  output reg WB_reg_write_en

);
// [0:2] unit ID, [3:130] 128-bit result, [131:137] reg_dst, [138:141] latency, [142] RegWr
reg [0:142] packed_result;
// reg [0:142] packed_result_1stage, packed_result_2stage, packed_result_3stage, packed_result_4stage, packed_result_5stage, packed_result_6stage, packed_result_7stage;

reg [0:127] result;
reg [0:2] unit_id;
reg [0:6] reg_dst;
reg [0:3] latency;
reg reg_wr;

reg [0:127] FX1_result;


FX1_ALU fx1_inst (
  .instr_id(instr_id),
  .ra(ra_data),
  .rb(rb_data),
  .rc(rc_data),
  .imme7(imme7),
  .imme10(imme10),
  .imme16(imme16),
  .imme18(imme18),
  .result(FX1_result)
);

// FX2 unit

// SP unit

// BYTE unit


always @(*) begin

  case (unit_id) 
    3'b000: result <= FX1_result;
    // 3'b001: result <= FX2_result;
    // 3'b010: result <= SP_result;  
    // 3'b011: result <= BYTE_result;
  endcase

  packed_result <= {unit_id, result, reg_dst, latency, reg_wr};

end

always @(posedge clk or posedge rst) begin
  if (rst) begin
    packed_result_1stage <= 0;
    packed_result_2stage <= 0;
    packed_result_3stage <= 0;
    packed_result_4stage <= 0;
    packed_result_5stage <= 0;
    packed_result_6stage <= 0;
    packed_result_7stage <= 0;
  end
  else begin
    packed_result_1stage <= packed_result;
    packed_result_2stage <= packed_result_1stage;
    packed_result_3stage <= packed_result_2stage;
    packed_result_4stage <= packed_result_3stage;
    packed_result_5stage <= packed_result_4stage;
    packed_result_6stage <= packed_result_5stage;
    packed_result_7stage <= packed_result_6stage;
    WB_reg_write_addr <= packed_result_7stage[131:137];
    WB_reg_write_data <= packed_result_7stage[3:130];
    WB_reg_write_en <= packed_result_7stage[142];
  end
end





endmodule

source_code/tb_Even_Pipe.v
// Dummy FX1_ALU module definition for simulation
module FX1_ALU(
  input  [0:6]   instr_id,
  input  [0:127] ra,
  input  [0:127] rb,
  input  [0:127] rc,
  input  [0:7]   imme7,
  input  [0:9]   imme10,
  input  [0:15]  imme16,
  input  [0:17]  imme18,
  output reg [0:127] result
);
  // Simple operation: for example, add ra and rb.
  always @(*) begin
    result = ra + rb;
  end
endmodule

// Testbench for Even_Pipe module
module tb_even_pipe;

  // Declare testbench signals (inputs as regs, outputs as wires)
  reg clk;
  reg rst;
  reg [0:31] full_isntr;
  reg [0:6]  instr_id;
  reg [0:6]  reg_dst;
  reg [0:2]  unit_id;
  reg [0:3]  latency;
  reg        reg_wr;
  reg [0:127] ra_data;
  reg [0:127] rb_data;
  reg [0:127] rc_data;
  reg [0:7]   imme7;
  reg [0:9]   imme10;
  reg [0:15]  imme16;
  reg [0:17]  imme18;

  wire [0:142] packed_result_1stage;
  wire [0:142] packed_result_2stage;
  wire [0:142] packed_result_3stage;
  wire [0:142] packed_result_4stage;
  wire [0:142] packed_result_5stage;
  wire [0:142] packed_result_6stage;
  wire [0:142] packed_result_7stage;
  wire [0:6]   WB_reg_write_addr;
  wire [0:127] WB_reg_write_data;
  wire         WB_reg_write_en;

  // Instantiate the device under test (DUT)
  Even_Pipe dut (
    .clk(clk),
    .rst(rst),
    .full_isntr(full_isntr),
    .instr_id(instr_id),
    .reg_dst(reg_dst),
    .unit_id(unit_id),
    .latency(latency),
    .reg_wr(reg_wr),
    .ra_data(ra_data),
    .rb_data(rb_data),
    .rc_data(rc_data),
    .imme7(imme7),
    .imme10(imme10),
    .imme16(imme16),
    .imme18(imme18),
    .packed_result_1stage(packed_result_1stage),
    .packed_result_2stage(packed_result_2stage),
    .packed_result_3stage(packed_result_3stage),
    .packed_result_4stage(packed_result_4stage),
    .packed_result_5stage(packed_result_5stage),
    .packed_result_6stage(packed_result_6stage),
    .packed_result_7stage(packed_result_7stage),
    .WB_reg_write_addr(WB_reg_write_addr),
    .WB_reg_write_data(WB_reg_write_data),
    .WB_reg_write_en(WB_reg_write_en)
  );

  // Clock generation: 10 time-unit period
  initial begin
    clk = 0;
    forever #5 clk = ~clk;
  end

  // Stimulus: apply reset and then drive test vectors
  initial begin
    // Initialize inputs and assert reset
    rst = 1;
    full_isntr = 32'hFFFFFFFF;
    instr_id    = 7'b1010101;
    reg_dst     = 7'b0000111;
    unit_id     = 3'b000;  // Use FX1 mode
    latency     = 4'b0010;
    reg_wr      = 1'b1;
    ra_data     = 128'h11111111111111111111111111111111;
    rb_data     = 128'h22222222222222222222222222222222;
    rc_data     = 128'h33333333333333333333333333333333;
    imme7       = 8'hAA;
    imme10      = 10'b1010101010;
    imme16      = 16'hBEEF;
    imme18      = 18'h2AAAA;

    #12 rst = 0;  // Deassert reset just after one clock cycle

    // Wait for about 10 clock cycles to observe the pipeline (7-stage delay)
    #100;

    // Apply a new set of input values to see pipelining in action
    full_isntr = 32'h12345678;
    instr_id    = 7'b0101010;
    reg_dst     = 7'b1110001;
    unit_id     = 3'b000;  // Remains in FX1 mode
    latency     = 4'b0101;
    reg_wr      = 1'b0;
    ra_data     = 128'hAAAAAAAAAAAAAAAAAAAAAAAAAAAAAAAA;
    rb_data     = 128'hBBBBBBBBBBBBBBBBBBBBBBBBBBBBBBBB;
    rc_data     = 128'hCCCCCCCCCCCCCCCCCCCCCCCCCCCCCCCC;
    imme7       = 8'h55;
    imme10      = 10'b0101010101;
    imme16      = 16'hFACE;
    imme18      = 18'h15555;

    #100;
    $finish;
  end

  // Monitor the WB stage outputs (which reflect the data after 7 pipeline stages)
  initial begin
    $monitor("Time=%0t | WB_reg_write_addr=%h | WB_reg_write_data=%h | WB_reg_write_en=%b",
             $time, WB_reg_write_addr, WB_reg_write_data, WB_reg_write_en);
  end

  initial begin
    $dumpfile("waveform.vcd");  // Dump to a VCD file
    $dumpvars(0, tb_even_pipe);  // Dump all signals in tb_even_pipe
  end 


endmodule

source_code/waveform.vcd
$date
    Mar  7, 2025  11:48:39
$end
$version
    TOOL:	xmsim	24.09-s001
$end
$timescale
    1 ns
$end

$scope module tb_even_pipe $end
$var reg       1 !    clk $end
$var reg       1 "    rst $end
$var reg      32 #    full_isntr [0:31] $end
$var reg       7 $    instr_id [0:6] $end
$var reg       7 %    reg_dst [0:6] $end
$var reg       3 &    unit_id [0:2] $end
$var reg       4 '    latency [0:3] $end
$var reg       1 (    reg_wr $end
$var reg      128 )    ra_data [0:127] $end
$var reg      128 *    rb_data [0:127] $end
$var reg      128 +    rc_data [0:127] $end
$var reg       8 ,    imme7 [0:7] $end
$var reg      10 -    imme10 [0:9] $end
$var reg      16 .    imme16 [0:15] $end
$var reg      18 /    imme18 [0:17] $end
$var wire     143 0    packed_result_1stage [0:142] $end
$var wire     143 1    packed_result_2stage [0:142] $end
$var wire     143 2    packed_result_3stage [0:142] $end
$var wire     143 3    packed_result_4stage [0:142] $end
$var wire     143 4    packed_result_5stage [0:142] $end
$var wire     143 5    packed_result_6stage [0:142] $end
$var wire     143 6    packed_result_7stage [0:142] $end
$var wire      7 7    WB_reg_write_addr [0:6] $end
$var wire     128 8    WB_reg_write_data [0:127] $end
$var wire      1 9    WB_reg_write_en  $end

$scope module dut $end
$var wire      1 :    clk  $end
$var wire      1 ;    rst  $end
$var wire     32 <    full_isntr [0:31] $end
$var wire      7 =    instr_id [0:6] $end
$var wire      7 >    reg_dst [0:6] $end
$var wire      3 ?    unit_id [0:2] $end
$var wire      4 @    latency [0:3] $end
$var wire      1 A    reg_wr  $end
$var wire     128 B    ra_data [0:127] $end
$var wire     128 C    rb_data [0:127] $end
$var wire     128 D    rc_data [0:127] $end
$var wire      8 E    imme7 [0:7] $end
$var wire     10 F    imme10 [0:9] $end
$var wire     16 G    imme16 [0:15] $end
$var wire     18 H    imme18 [0:17] $end
$var reg      143 I    packed_result_1stage [0:142] $end
$var reg      143 J    packed_result_2stage [0:142] $end
$var reg      143 K    packed_result_3stage [0:142] $end
$var reg      143 L    packed_result_4stage [0:142] $end
$var reg      143 M    packed_result_5stage [0:142] $end
$var reg      143 N    packed_result_6stage [0:142] $end
$var reg      143 O    packed_result_7stage [0:142] $end
$var reg       7 P    WB_reg_write_addr [0:6] $end
$var reg      128 Q    WB_reg_write_data [0:127] $end
$var reg       1 R    WB_reg_write_en $end
$var reg      143 S    packed_result [0:142] $end
$var reg      128 T    result [0:127] $end
$var reg      128 U    FX1_result [0:127] $end

$scope module fx1_inst $end
$var wire      7 =    instr_id [0:6] $end
$var wire     128 B    ra [0:127] $end
$var wire     128 C    rb [0:127] $end
$var wire     128 D    rc [0:127] $end
$var wire      8 E    imme7 [0:7] $end
$var wire     10 F    imme10 [0:9] $end
$var wire     16 G    imme16 [0:15] $end
$var wire     18 H    imme18 [0:17] $end
$var reg      128 V    result [0:127] $end
$upscope $end

$upscope $end

$upscope $end

$enddefinitions $end
$dumpvars
0!
1"
b11111111111111111111111111111111 #
b1010101 $
b111 %
b0 &
b10 '
1(
b10001000100010001000100010001000100010001000100010001000100010001000100010001000100010001000100010001000100010001000100010001 )
b100010001000100010001000100010001000100010001000100010001000100010001000100010001000100010001000100010001000100010001000100010 *
b110011001100110011001100110011001100110011001100110011001100110011001100110011001100110011001100110011001100110011001100110011 +
b10101010 ,
b1010101010 -
b1011111011101111 .
b101010101010101010 /
b0 0
b0 1
b0 2
b0 3
b0 4
b0 5
b0 6
bx 7
bx 8
x9
0:
1;
b11111111111111111111111111111111 <
b1010101 =
b111 >
b0 ?
b10 @
1A
b10001000100010001000100010001000100010001000100010001000100010001000100010001000100010001000100010001000100010001000100010001 B
b100010001000100010001000100010001000100010001000100010001000100010001000100010001000100010001000100010001000100010001000100010 C
b110011001100110011001100110011001100110011001100110011001100110011001100110011001100110011001100110011001100110011001100110011 D
b10101010 E
b1010101010 F
b1011111011101111 G
b101010101010101010 H
b0 I
b0 J
b0 K
b0 L
b0 M
b0 N
b0 O
bx P
bx Q
xR
b110011001100110011001100110011001100110011001100110011001100110011001100110011001100110011001100110011001100110011001100110011000011100101 S
b110011001100110011001100110011001100110011001100110011001100110011001100110011001100110011001100110011001100110011001100110011 T
b110011001100110011001100110011001100110011001100110011001100110011001100110011001100110011001100110011001100110011001100110011 U
b110011001100110011001100110011001100110011001100110011001100110011001100110011001100110011001100110011001100110011001100110011 V
$end
#5
1!
1:
#10
0!
0:
#12
0"
0;
#15
1!
1:
b110011001100110011001100110011001100110011001100110011001100110011001100110011001100110011001100110011001100110011001100110011000011100101 I
b0 P
b0 Q
0R
09
b0 8
b0 7
b110011001100110011001100110011001100110011001100110011001100110011001100110011001100110011001100110011001100110011001100110011000011100101 0
#20
0!
0:
#25
1!
1:
b110011001100110011001100110011001100110011001100110011001100110011001100110011001100110011001100110011001100110011001100110011000011100101 J
b110011001100110011001100110011001100110011001100110011001100110011001100110011001100110011001100110011001100110011001100110011000011100101 1
#30
0!
0:
#35
1!
1:
b110011001100110011001100110011001100110011001100110011001100110011001100110011001100110011001100110011001100110011001100110011000011100101 K
b110011001100110011001100110011001100110011001100110011001100110011001100110011001100110011001100110011001100110011001100110011000011100101 2
#40
0!
0:
#45
1!
1:
b110011001100110011001100110011001100110011001100110011001100110011001100110011001100110011001100110011001100110011001100110011000011100101 L
b110011001100110011001100110011001100110011001100110011001100110011001100110011001100110011001100110011001100110011001100110011000011100101 3
#50
0!
0:
#55
1!
1:
b110011001100110011001100110011001100110011001100110011001100110011001100110011001100110011001100110011001100110011001100110011000011100101 M
b110011001100110011001100110011001100110011001100110011001100110011001100110011001100110011001100110011001100110011001100110011000011100101 4
#60
0!
0:
#65
1!
1:
b110011001100110011001100110011001100110011001100110011001100110011001100110011001100110011001100110011001100110011001100110011000011100101 N
b110011001100110011001100110011001100110011001100110011001100110011001100110011001100110011001100110011001100110011001100110011000011100101 5
#70
0!
0:
#75
1!
1:
b110011001100110011001100110011001100110011001100110011001100110011001100110011001100110011001100110011001100110011001100110011000011100101 O
b110011001100110011001100110011001100110011001100110011001100110011001100110011001100110011001100110011001100110011001100110011000011100101 6
#80
0!
0:
#85
1!
1:
b111 P
b110011001100110011001100110011001100110011001100110011001100110011001100110011001100110011001100110011001100110011001100110011 Q
1R
19
b110011001100110011001100110011001100110011001100110011001100110011001100110011001100110011001100110011001100110011001100110011 8
b111 7
#90
0!
0:
#95
1!
1:
#100
0!
0:
#105
1!
1:
#110
0!
0:
#112
b10010001101000101011001111000 #
b101010 $
b1110001 %
b101 '
0(
b10101010101010101010101010101010101010101010101010101010101010101010101010101010101010101010101010101010101010101010101010101010 )
b10111011101110111011101110111011101110111011101110111011101110111011101110111011101110111011101110111011101110111011101110111011 *
b11001100110011001100110011001100110011001100110011001100110011001100110011001100110011001100110011001100110011001100110011001100 +
b1010101 ,
b101010101 -
b1111101011001110 .
b10101010101010101 /
b10010001101000101011001111000 <
b10101010101010101 H
b1111101011001110 G
b101010101 F
b1010101 E
b11001100110011001100110011001100110011001100110011001100110011001100110011001100110011001100110011001100110011001100110011001100 D
b10111011101110111011101110111011101110111011101110111011101110111011101110111011101110111011101110111011101110111011101110111011 C
b10101010101010101010101010101010101010101010101010101010101010101010101010101010101010101010101010101010101010101010101010101010 B
0A
b101 @
b1110001 >
b101010 =
b1100110011001100110011001100110011001100110011001100110011001100110011001100110011001100110011001100110011001100110011001100101 V
b1100110011001100110011001100110011001100110011001100110011001100110011001100110011001100110011001100110011001100110011001100101 U
b110011001100110011001100110011001100110011001100110011001100110011001100110011001100110011001100110011001100110011001100110011111000101010 S
b1100110011001100110011001100110011001100110011001100110011001100110011001100110011001100110011001100110011001100110011001100101 T
b1100110011001100110011001100110011001100110011001100110011001100110011001100110011001100110011001100110011001100110011001100101111000101010 S
#115
1!
1:
b1100110011001100110011001100110011001100110011001100110011001100110011001100110011001100110011001100110011001100110011001100101111000101010 I
b1100110011001100110011001100110011001100110011001100110011001100110011001100110011001100110011001100110011001100110011001100101111000101010 0
#120
0!
0:
#125
1!
1:
b1100110011001100110011001100110011001100110011001100110011001100110011001100110011001100110011001100110011001100110011001100101111000101010 J
b1100110011001100110011001100110011001100110011001100110011001100110011001100110011001100110011001100110011001100110011001100101111000101010 1
#130
0!
0:
#135
1!
1:
b1100110011001100110011001100110011001100110011001100110011001100110011001100110011001100110011001100110011001100110011001100101111000101010 K
b1100110011001100110011001100110011001100110011001100110011001100110011001100110011001100110011001100110011001100110011001100101111000101010 2
#140
0!
0:
#145
1!
1:
b1100110011001100110011001100110011001100110011001100110011001100110011001100110011001100110011001100110011001100110011001100101111000101010 L
b1100110011001100110011001100110011001100110011001100110011001100110011001100110011001100110011001100110011001100110011001100101111000101010 3
#150
0!
0:
#155
1!
1:
b1100110011001100110011001100110011001100110011001100110011001100110011001100110011001100110011001100110011001100110011001100101111000101010 M
b1100110011001100110011001100110011001100110011001100110011001100110011001100110011001100110011001100110011001100110011001100101111000101010 4
#160
0!
0:
#165
1!
1:
b1100110011001100110011001100110011001100110011001100110011001100110011001100110011001100110011001100110011001100110011001100101111000101010 N
b1100110011001100110011001100110011001100110011001100110011001100110011001100110011001100110011001100110011001100110011001100101111000101010 5
#170
0!
0:
#175
1!
1:
b1100110011001100110011001100110011001100110011001100110011001100110011001100110011001100110011001100110011001100110011001100101111000101010 O
b1100110011001100110011001100110011001100110011001100110011001100110011001100110011001100110011001100110011001100110011001100101111000101010 6
#180
0!
0:
#185
1!
1:
b1110001 P
b1100110011001100110011001100110011001100110011001100110011001100110011001100110011001100110011001100110011001100110011001100101 Q
0R
09
b1100110011001100110011001100110011001100110011001100110011001100110011001100110011001100110011001100110011001100110011001100101 8
b1110001 7
